gymnasium_snake_game/__init__.py
gymnasium_snake_game/version.py
gymnasium_snake_game/environment/__init__.py
gymnasium_snake_game/environment/core.py
gymnasium_snake_game/environment/snake_env.py
gymnasium_snake_game/environment/utils.py
gymnasium_snake_game-0.2.1.dist-info/LICENSE
gymnasium_snake_game-0.2.1.dist-info/METADATA
gymnasium_snake_game-0.2.1.dist-info/WHEEL
gymnasium_snake_game-0.2.1.dist-info/top_level.txt
gymnasium_snake_game-0.2.1.dist-info/RECORD
