Metadata-Version: 2.1
Name: gymnasium_snake_game
Version: 0.2.1
Summary: Snake game for Farama Gymnasium
Home-page: https://github.com/lychanl/Gymnasium_Snake_Game
Author: Jakub Łyskawa
License: MIT
Keywords: ai,rl,snake
Platform: any
Classifier: License :: OSI Approved :: MIT License
Classifier: Development Status :: 3 - Alpha
Classifier: Operating System :: OS Independent
Classifier: Topic :: Scientific/Engineering :: Artificial Intelligence
Classifier: Topic :: Games/Entertainment :: Arcade
Classifier: Programming Language :: Python :: 3.10
Requires-Python: >=3.0
License-File: LICENSE
Requires-Dist: pygame>=2.1.0
Requires-Dist: numpy>=1.21
Requires-Dist: gymnasium>=0.29
